[{"gen": 0, "nevals": 40, "steps": 197021}, {"gen": 1, "nevals": 40, "steps": 197024}, {"gen": 2, "nevals": 40, "steps": 196075}, {"gen": 3, "nevals": 40, "steps": 197019}, {"gen": 4, "nevals": 40, "steps": 198026}, {"gen": 5, "nevals": 40, "steps": 198044}, {"gen": 6, "nevals": 40, "steps": 197023}, {"gen": 7, "nevals": 40, "steps": 197043}, {"gen": 8, "nevals": 40, "steps": 199005}, {"gen": 9, "nevals": 40, "steps": 196012}, {"gen": 10, "nevals": 40, "steps": 196036}, {"gen": 11, "nevals": 40, "steps": 196027}, {"gen": 12, "nevals": 40, "steps": 198015}, {"gen": 13, "nevals": 40, "steps": 197045}, {"gen": 14, "nevals": 40, "steps": 194045}, {"gen": 15, "nevals": 40, "steps": 196029}, {"gen": 16, "nevals": 40, "steps": 195070}, {"gen": 17, "nevals": 40, "steps": 199003}, {"gen": 18, "nevals": 40, "steps": 198011}, {"gen": 19, "nevals": 40, "steps": 196032}, {"gen": 20, "nevals": 40, "steps": 196043}, {"gen": 21, "nevals": 40, "steps": 192057}, {"gen": 22, "nevals": 40, "steps": 196021}, {"gen": 23, "nevals": 40, "steps": 193065}, {"gen": 24, "nevals": 40, "steps": 195034}, {"gen": 25, "nevals": 40, "steps": 196040}, {"gen": 26, "nevals": 40, "steps": 194037}, {"gen": 27, "nevals": 40, "steps": 194058}, {"gen": 28, "nevals": 40, "steps": 195040}, {"gen": 29, "nevals": 40, "steps": 197020}, {"gen": 30, "nevals": 40, "steps": 196025}, {"gen": 31, "nevals": 40, "steps": 199005}, {"gen": 32, "nevals": 40, "steps": 198023}, {"gen": 33, "nevals": 40, "steps": 192160}, {"gen": 34, "nevals": 40, "steps": 197032}, {"gen": 35, "nevals": 40, "steps": 195041}, {"gen": 36, "nevals": 40, "steps": 198009}, {"gen": 37, "nevals": 40, "steps": 199011}, {"gen": 38, "nevals": 40, "steps": 196044}, {"gen": 39, "nevals": 40, "steps": 198006}, {"gen": 40, "nevals": 40, "steps": 194043}, {"gen": 41, "nevals": 40, "steps": 196032}, {"gen": 42, "nevals": 40, "steps": 197027}, {"gen": 43, "nevals": 40, "steps": 199022}, {"gen": 44, "nevals": 40, "steps": 195032}, {"gen": 45, "nevals": 40, "steps": 197025}, {"gen": 46, "nevals": 40, "steps": 198010}, {"gen": 47, "nevals": 40, "steps": 195036}, {"gen": 48, "nevals": 40, "steps": 196012}, {"gen": 49, "nevals": 40, "steps": 200000}, {"gen": 50, "nevals": 40, "steps": 196015}, {"gen": 51, "nevals": 40, "steps": 193051}, {"gen": 52, "nevals": 40, "steps": 199001}, {"gen": 53, "nevals": 40, "steps": 199055}, {"gen": 54, "nevals": 40, "steps": 200000}, {"gen": 55, "nevals": 40, "steps": 199003}, {"gen": 56, "nevals": 40, "steps": 198007}, {"gen": 57, "nevals": 40, "steps": 199015}, {"gen": 58, "nevals": 40, "steps": 197012}, {"gen": 59, "nevals": 40, "steps": 197047}, {"gen": 60, "nevals": 40, "steps": 199010}, {"gen": 61, "nevals": 40, "steps": 198016}, {"gen": 62, "nevals": 40, "steps": 192087}, {"gen": 63, "nevals": 40, "steps": 194067}, {"gen": 64, "nevals": 40, "steps": 197028}, {"gen": 65, "nevals": 40, "steps": 196037}, {"gen": 66, "nevals": 40, "steps": 199021}, {"gen": 67, "nevals": 40, "steps": 199005}, {"gen": 68, "nevals": 40, "steps": 197028}, {"gen": 69, "nevals": 40, "steps": 196027}, {"gen": 70, "nevals": 40, "steps": 196049}, {"gen": 71, "nevals": 40, "steps": 197009}, {"gen": 72, "nevals": 40, "steps": 198019}, {"gen": 73, "nevals": 40, "steps": 198096}, {"gen": 74, "nevals": 40, "steps": 199003}, {"gen": 75, "nevals": 40, "steps": 198023}, {"gen": 76, "nevals": 40, "steps": 196040}, {"gen": 77, "nevals": 40, "steps": 197027}, {"gen": 78, "nevals": 40, "steps": 195044}, {"gen": 79, "nevals": 40, "steps": 196064}, {"gen": 80, "nevals": 40, "steps": 199010}, {"gen": 81, "nevals": 40, "steps": 198039}, {"gen": 82, "nevals": 40, "steps": 199013}, {"gen": 83, "nevals": 40, "steps": 195016}, {"gen": 84, "nevals": 40, "steps": 197029}, {"gen": 85, "nevals": 40, "steps": 194057}, {"gen": 86, "nevals": 40, "steps": 197067}, {"gen": 87, "nevals": 40, "steps": 199009}, {"gen": 88, "nevals": 40, "steps": 194057}, {"gen": 89, "nevals": 40, "steps": 195081}, {"gen": 90, "nevals": 40, "steps": 195055}, {"gen": 91, "nevals": 40, "steps": 199009}, {"gen": 92, "nevals": 40, "steps": 196031}, {"gen": 93, "nevals": 40, "steps": 190093}, {"gen": 94, "nevals": 40, "steps": 192069}, {"gen": 95, "nevals": 40, "steps": 191060}, {"gen": 96, "nevals": 40, "steps": 193064}, {"gen": 97, "nevals": 40, "steps": 199023}, {"gen": 98, "nevals": 40, "steps": 196039}, {"gen": 99, "nevals": 40, "steps": 195047}]