[{"gen": 0, "nevals": 500, "steps": 217466}, {"gen": 1, "nevals": 500, "steps": 202841}, {"gen": 2, "nevals": 500, "steps": 207805}, {"gen": 3, "nevals": 500, "steps": 213285}, {"gen": 4, "nevals": 500, "steps": 203108}, {"gen": 5, "nevals": 500, "steps": 207724}, {"gen": 6, "nevals": 500, "steps": 224707}, {"gen": 7, "nevals": 500, "steps": 203724}, {"gen": 8, "nevals": 500, "steps": 206175}, {"gen": 9, "nevals": 500, "steps": 211587}, {"gen": 10, "nevals": 500, "steps": 240154}, {"gen": 11, "nevals": 500, "steps": 208277}, {"gen": 12, "nevals": 500, "steps": 224284}, {"gen": 13, "nevals": 500, "steps": 224161}, {"gen": 14, "nevals": 500, "steps": 232569}, {"gen": 15, "nevals": 500, "steps": 227948}, {"gen": 16, "nevals": 500, "steps": 240457}, {"gen": 17, "nevals": 500, "steps": 208114}, {"gen": 18, "nevals": 500, "steps": 237505}, {"gen": 19, "nevals": 500, "steps": 254760}, {"gen": 20, "nevals": 500, "steps": 241862}, {"gen": 21, "nevals": 500, "steps": 237559}, {"gen": 22, "nevals": 500, "steps": 228853}, {"gen": 23, "nevals": 500, "steps": 245709}, {"gen": 24, "nevals": 500, "steps": 254172}, {"gen": 25, "nevals": 500, "steps": 240134}, {"gen": 26, "nevals": 500, "steps": 218111}, {"gen": 27, "nevals": 500, "steps": 237353}, {"gen": 28, "nevals": 500, "steps": 265908}, {"gen": 29, "nevals": 500, "steps": 291501}, {"gen": 30, "nevals": 500, "steps": 299931}, {"gen": 31, "nevals": 500, "steps": 346868}, {"gen": 32, "nevals": 500, "steps": 375009}, {"gen": 33, "nevals": 500, "steps": 305326}, {"gen": 34, "nevals": 500, "steps": 313602}, {"gen": 35, "nevals": 500, "steps": 338353}, {"gen": 36, "nevals": 500, "steps": 365155}, {"gen": 37, "nevals": 500, "steps": 352195}, {"gen": 38, "nevals": 500, "steps": 395924}, {"gen": 39, "nevals": 500, "steps": 434617}, {"gen": 40, "nevals": 500, "steps": 369528}, {"gen": 41, "nevals": 500, "steps": 370596}, {"gen": 42, "nevals": 500, "steps": 431727}, {"gen": 43, "nevals": 500, "steps": 462406}, {"gen": 44, "nevals": 500, "steps": 435978}, {"gen": 45, "nevals": 500, "steps": 382692}, {"gen": 46, "nevals": 500, "steps": 438312}, {"gen": 47, "nevals": 500, "steps": 440686}, {"gen": 48, "nevals": 500, "steps": 472692}, {"gen": 49, "nevals": 500, "steps": 434973}, {"gen": 50, "nevals": 500, "steps": 415235}, {"gen": 51, "nevals": 500, "steps": 407076}, {"gen": 52, "nevals": 500, "steps": 378981}, {"gen": 53, "nevals": 500, "steps": 385801}, {"gen": 54, "nevals": 500, "steps": 408957}, {"gen": 55, "nevals": 500, "steps": 442112}, {"gen": 56, "nevals": 500, "steps": 461899}, {"gen": 57, "nevals": 500, "steps": 454322}, {"gen": 58, "nevals": 500, "steps": 390668}, {"gen": 59, "nevals": 500, "steps": 374980}, {"gen": 60, "nevals": 500, "steps": 336929}, {"gen": 61, "nevals": 500, "steps": 386652}, {"gen": 62, "nevals": 500, "steps": 392054}, {"gen": 63, "nevals": 500, "steps": 399476}, {"gen": 64, "nevals": 500, "steps": 427260}, {"gen": 65, "nevals": 500, "steps": 427015}, {"gen": 66, "nevals": 500, "steps": 398632}, {"gen": 67, "nevals": 500, "steps": 399302}, {"gen": 68, "nevals": 500, "steps": 360448}, {"gen": 69, "nevals": 500, "steps": 360361}, {"gen": 70, "nevals": 500, "steps": 384361}, {"gen": 71, "nevals": 500, "steps": 363420}, {"gen": 72, "nevals": 500, "steps": 423413}, {"gen": 73, "nevals": 500, "steps": 401352}, {"gen": 74, "nevals": 500, "steps": 445119}, {"gen": 75, "nevals": 500, "steps": 320316}, {"gen": 76, "nevals": 500, "steps": 370649}, {"gen": 77, "nevals": 500, "steps": 344166}, {"gen": 78, "nevals": 500, "steps": 401458}, {"gen": 79, "nevals": 500, "steps": 424205}, {"gen": 80, "nevals": 500, "steps": 365650}, {"gen": 81, "nevals": 500, "steps": 373899}, {"gen": 82, "nevals": 500, "steps": 419934}, {"gen": 83, "nevals": 500, "steps": 412179}, {"gen": 84, "nevals": 500, "steps": 403352}, {"gen": 85, "nevals": 500, "steps": 421488}, {"gen": 86, "nevals": 500, "steps": 413417}, {"gen": 87, "nevals": 500, "steps": 400041}, {"gen": 88, "nevals": 500, "steps": 415153}, {"gen": 89, "nevals": 500, "steps": 443367}, {"gen": 90, "nevals": 500, "steps": 440092}, {"gen": 91, "nevals": 500, "steps": 410135}, {"gen": 92, "nevals": 500, "steps": 426605}, {"gen": 93, "nevals": 500, "steps": 461818}, {"gen": 94, "nevals": 500, "steps": 494817}, {"gen": 95, "nevals": 500, "steps": 478694}, {"gen": 96, "nevals": 500, "steps": 476810}, {"gen": 97, "nevals": 500, "steps": 527997}, {"gen": 98, "nevals": 500, "steps": 534295}, {"gen": 99, "nevals": 500, "steps": 525577}, {"gen": 100, "nevals": 500, "steps": 539059}, {"gen": 101, "nevals": 500, "steps": 479571}, {"gen": 102, "nevals": 500, "steps": 544884}, {"gen": 103, "nevals": 500, "steps": 568937}, {"gen": 104, "nevals": 500, "steps": 519539}, {"gen": 105, "nevals": 500, "steps": 548024}, {"gen": 106, "nevals": 500, "steps": 588619}, {"gen": 107, "nevals": 500, "steps": 521747}, {"gen": 108, "nevals": 500, "steps": 543350}, {"gen": 109, "nevals": 500, "steps": 557661}, {"gen": 110, "nevals": 500, "steps": 544289}, {"gen": 111, "nevals": 500, "steps": 455331}, {"gen": 112, "nevals": 500, "steps": 448353}, {"gen": 113, "nevals": 500, "steps": 456514}, {"gen": 114, "nevals": 500, "steps": 536858}, {"gen": 115, "nevals": 500, "steps": 485834}, {"gen": 116, "nevals": 500, "steps": 434434}, {"gen": 117, "nevals": 500, "steps": 435991}, {"gen": 118, "nevals": 500, "steps": 491799}, {"gen": 119, "nevals": 500, "steps": 577473}, {"gen": 120, "nevals": 500, "steps": 654713}, {"gen": 121, "nevals": 500, "steps": 554744}, {"gen": 122, "nevals": 500, "steps": 649809}, {"gen": 123, "nevals": 500, "steps": 658321}, {"gen": 124, "nevals": 500, "steps": 647375}, {"gen": 125, "nevals": 500, "steps": 531799}, {"gen": 126, "nevals": 500, "steps": 533435}, {"gen": 127, "nevals": 500, "steps": 516964}, {"gen": 128, "nevals": 500, "steps": 589682}, {"gen": 129, "nevals": 500, "steps": 653917}, {"gen": 130, "nevals": 500, "steps": 677729}, {"gen": 131, "nevals": 500, "steps": 578542}, {"gen": 132, "nevals": 500, "steps": 552643}, {"gen": 133, "nevals": 500, "steps": 564461}, {"gen": 134, "nevals": 500, "steps": 490908}, {"gen": 135, "nevals": 500, "steps": 544799}, {"gen": 136, "nevals": 500, "steps": 497415}, {"gen": 137, "nevals": 500, "steps": 562428}, {"gen": 138, "nevals": 500, "steps": 521634}, {"gen": 139, "nevals": 500, "steps": 537386}, {"gen": 140, "nevals": 500, "steps": 518912}, {"gen": 141, "nevals": 500, "steps": 484708}, {"gen": 142, "nevals": 500, "steps": 472196}, {"gen": 143, "nevals": 500, "steps": 479517}, {"gen": 144, "nevals": 500, "steps": 585692}, {"gen": 145, "nevals": 500, "steps": 564521}, {"gen": 146, "nevals": 500, "steps": 530154}, {"gen": 147, "nevals": 500, "steps": 528023}, {"gen": 148, "nevals": 500, "steps": 431931}, {"gen": 149, "nevals": 500, "steps": 551333}, {"gen": 150, "nevals": 500, "steps": 524541}, {"gen": 151, "nevals": 500, "steps": 575315}, {"gen": 152, "nevals": 500, "steps": 575261}, {"gen": 153, "nevals": 500, "steps": 573471}, {"gen": 154, "nevals": 500, "steps": 602349}, {"gen": 155, "nevals": 500, "steps": 618554}, {"gen": 156, "nevals": 500, "steps": 610280}, {"gen": 157, "nevals": 500, "steps": 598800}, {"gen": 158, "nevals": 500, "steps": 556759}, {"gen": 159, "nevals": 500, "steps": 644593}, {"gen": 160, "nevals": 500, "steps": 664325}, {"gen": 161, "nevals": 500, "steps": 606322}, {"gen": 162, "nevals": 500, "steps": 521103}, {"gen": 163, "nevals": 500, "steps": 587328}, {"gen": 164, "nevals": 500, "steps": 619198}, {"gen": 165, "nevals": 500, "steps": 605203}, {"gen": 166, "nevals": 500, "steps": 628737}, {"gen": 167, "nevals": 500, "steps": 579518}, {"gen": 168, "nevals": 500, "steps": 628318}, {"gen": 169, "nevals": 500, "steps": 672053}, {"gen": 170, "nevals": 500, "steps": 707931}, {"gen": 171, "nevals": 500, "steps": 594060}, {"gen": 172, "nevals": 500, "steps": 661961}, {"gen": 173, "nevals": 500, "steps": 625706}, {"gen": 174, "nevals": 500, "steps": 502302}, {"gen": 175, "nevals": 500, "steps": 509781}, {"gen": 176, "nevals": 500, "steps": 510496}, {"gen": 177, "nevals": 500, "steps": 528225}, {"gen": 178, "nevals": 500, "steps": 447128}, {"gen": 179, "nevals": 500, "steps": 399068}, {"gen": 180, "nevals": 500, "steps": 444568}, {"gen": 181, "nevals": 500, "steps": 520018}, {"gen": 182, "nevals": 500, "steps": 601478}, {"gen": 183, "nevals": 500, "steps": 582324}, {"gen": 184, "nevals": 500, "steps": 596915}, {"gen": 185, "nevals": 500, "steps": 563241}, {"gen": 186, "nevals": 500, "steps": 612163}, {"gen": 187, "nevals": 500, "steps": 573781}, {"gen": 188, "nevals": 500, "steps": 608216}, {"gen": 189, "nevals": 500, "steps": 506721}, {"gen": 190, "nevals": 500, "steps": 580195}, {"gen": 191, "nevals": 500, "steps": 613035}, {"gen": 192, "nevals": 500, "steps": 692516}, {"gen": 193, "nevals": 500, "steps": 591509}, {"gen": 194, "nevals": 500, "steps": 634822}, {"gen": 195, "nevals": 500, "steps": 666902}, {"gen": 196, "nevals": 500, "steps": 623678}, {"gen": 197, "nevals": 500, "steps": 618492}, {"gen": 198, "nevals": 500, "steps": 644559}, {"gen": 199, "nevals": 500, "steps": 610031}, {"gen": 200, "nevals": 500, "steps": 636247}]