[{"gen": 0, "nevals": 500, "steps": 218495}, {"gen": 1, "nevals": 500, "steps": 214973}, {"gen": 2, "nevals": 500, "steps": 208457}, {"gen": 3, "nevals": 500, "steps": 208211}, {"gen": 4, "nevals": 500, "steps": 194864}, {"gen": 5, "nevals": 500, "steps": 214095}, {"gen": 6, "nevals": 500, "steps": 223054}, {"gen": 7, "nevals": 500, "steps": 235593}, {"gen": 8, "nevals": 500, "steps": 244912}, {"gen": 9, "nevals": 500, "steps": 240760}, {"gen": 10, "nevals": 500, "steps": 232003}, {"gen": 11, "nevals": 500, "steps": 240703}, {"gen": 12, "nevals": 500, "steps": 231816}, {"gen": 13, "nevals": 500, "steps": 244231}, {"gen": 14, "nevals": 500, "steps": 280162}, {"gen": 15, "nevals": 500, "steps": 278959}, {"gen": 16, "nevals": 500, "steps": 245207}, {"gen": 17, "nevals": 500, "steps": 272025}, {"gen": 18, "nevals": 500, "steps": 285452}, {"gen": 19, "nevals": 500, "steps": 272538}, {"gen": 20, "nevals": 500, "steps": 315226}, {"gen": 21, "nevals": 500, "steps": 382383}, {"gen": 22, "nevals": 500, "steps": 354064}, {"gen": 23, "nevals": 500, "steps": 331684}, {"gen": 24, "nevals": 500, "steps": 335824}, {"gen": 25, "nevals": 500, "steps": 311754}, {"gen": 26, "nevals": 500, "steps": 315526}, {"gen": 27, "nevals": 500, "steps": 333758}, {"gen": 28, "nevals": 500, "steps": 306772}, {"gen": 29, "nevals": 500, "steps": 326896}, {"gen": 30, "nevals": 500, "steps": 330334}, {"gen": 31, "nevals": 500, "steps": 326163}, {"gen": 32, "nevals": 500, "steps": 309481}, {"gen": 33, "nevals": 500, "steps": 325745}, {"gen": 34, "nevals": 500, "steps": 292444}, {"gen": 35, "nevals": 500, "steps": 322584}, {"gen": 36, "nevals": 500, "steps": 297117}, {"gen": 37, "nevals": 500, "steps": 330088}, {"gen": 38, "nevals": 500, "steps": 297670}, {"gen": 39, "nevals": 500, "steps": 333662}, {"gen": 40, "nevals": 500, "steps": 317618}, {"gen": 41, "nevals": 500, "steps": 311480}, {"gen": 42, "nevals": 500, "steps": 332650}, {"gen": 43, "nevals": 500, "steps": 342634}, {"gen": 44, "nevals": 500, "steps": 389292}, {"gen": 45, "nevals": 500, "steps": 436831}, {"gen": 46, "nevals": 500, "steps": 353990}, {"gen": 47, "nevals": 500, "steps": 300247}, {"gen": 48, "nevals": 500, "steps": 326674}, {"gen": 49, "nevals": 500, "steps": 310788}, {"gen": 50, "nevals": 500, "steps": 290325}, {"gen": 51, "nevals": 500, "steps": 330780}, {"gen": 52, "nevals": 500, "steps": 362361}, {"gen": 53, "nevals": 500, "steps": 336711}, {"gen": 54, "nevals": 500, "steps": 377219}, {"gen": 55, "nevals": 500, "steps": 291826}, {"gen": 56, "nevals": 500, "steps": 383446}, {"gen": 57, "nevals": 500, "steps": 389910}, {"gen": 58, "nevals": 500, "steps": 380318}, {"gen": 59, "nevals": 500, "steps": 405234}, {"gen": 60, "nevals": 500, "steps": 416556}, {"gen": 61, "nevals": 500, "steps": 390107}, {"gen": 62, "nevals": 500, "steps": 352455}, {"gen": 63, "nevals": 500, "steps": 355683}, {"gen": 64, "nevals": 500, "steps": 388519}, {"gen": 65, "nevals": 500, "steps": 368859}, {"gen": 66, "nevals": 500, "steps": 377114}, {"gen": 67, "nevals": 500, "steps": 396645}, {"gen": 68, "nevals": 500, "steps": 365569}, {"gen": 69, "nevals": 500, "steps": 367553}, {"gen": 70, "nevals": 500, "steps": 373211}, {"gen": 71, "nevals": 500, "steps": 366309}, {"gen": 72, "nevals": 500, "steps": 381438}, {"gen": 73, "nevals": 500, "steps": 378182}, {"gen": 74, "nevals": 500, "steps": 364478}, {"gen": 75, "nevals": 500, "steps": 365520}, {"gen": 76, "nevals": 500, "steps": 353203}, {"gen": 77, "nevals": 500, "steps": 362017}, {"gen": 78, "nevals": 500, "steps": 313595}, {"gen": 79, "nevals": 500, "steps": 260374}, {"gen": 80, "nevals": 500, "steps": 330834}, {"gen": 81, "nevals": 500, "steps": 285107}, {"gen": 82, "nevals": 500, "steps": 318856}, {"gen": 83, "nevals": 500, "steps": 375123}, {"gen": 84, "nevals": 500, "steps": 334014}, {"gen": 85, "nevals": 500, "steps": 366978}, {"gen": 86, "nevals": 500, "steps": 408952}, {"gen": 87, "nevals": 500, "steps": 440338}, {"gen": 88, "nevals": 500, "steps": 428577}, {"gen": 89, "nevals": 500, "steps": 474933}, {"gen": 90, "nevals": 500, "steps": 453278}, {"gen": 91, "nevals": 500, "steps": 419579}, {"gen": 92, "nevals": 500, "steps": 384226}, {"gen": 93, "nevals": 500, "steps": 507764}, {"gen": 94, "nevals": 500, "steps": 443068}, {"gen": 95, "nevals": 500, "steps": 461266}, {"gen": 96, "nevals": 500, "steps": 403892}, {"gen": 97, "nevals": 500, "steps": 429367}, {"gen": 98, "nevals": 500, "steps": 465309}, {"gen": 99, "nevals": 500, "steps": 460542}, {"gen": 100, "nevals": 500, "steps": 435777}, {"gen": 101, "nevals": 500, "steps": 405793}, {"gen": 102, "nevals": 500, "steps": 437854}, {"gen": 103, "nevals": 500, "steps": 415608}, {"gen": 104, "nevals": 500, "steps": 413849}, {"gen": 105, "nevals": 500, "steps": 465819}, {"gen": 106, "nevals": 500, "steps": 476792}, {"gen": 107, "nevals": 500, "steps": 516116}, {"gen": 108, "nevals": 500, "steps": 560400}, {"gen": 109, "nevals": 500, "steps": 488532}, {"gen": 110, "nevals": 500, "steps": 522981}, {"gen": 111, "nevals": 500, "steps": 636698}, {"gen": 112, "nevals": 500, "steps": 530181}, {"gen": 113, "nevals": 500, "steps": 545292}, {"gen": 114, "nevals": 500, "steps": 517994}, {"gen": 115, "nevals": 500, "steps": 464225}, {"gen": 116, "nevals": 500, "steps": 454985}, {"gen": 117, "nevals": 500, "steps": 550497}, {"gen": 118, "nevals": 500, "steps": 520968}, {"gen": 119, "nevals": 500, "steps": 452622}, {"gen": 120, "nevals": 500, "steps": 579208}, {"gen": 121, "nevals": 500, "steps": 506873}, {"gen": 122, "nevals": 500, "steps": 693712}, {"gen": 123, "nevals": 500, "steps": 626830}, {"gen": 124, "nevals": 500, "steps": 625303}, {"gen": 125, "nevals": 500, "steps": 608095}, {"gen": 126, "nevals": 500, "steps": 576496}, {"gen": 127, "nevals": 500, "steps": 582592}, {"gen": 128, "nevals": 500, "steps": 544340}, {"gen": 129, "nevals": 500, "steps": 534668}, {"gen": 130, "nevals": 500, "steps": 615857}, {"gen": 131, "nevals": 500, "steps": 555220}, {"gen": 132, "nevals": 500, "steps": 563066}, {"gen": 133, "nevals": 500, "steps": 644416}, {"gen": 134, "nevals": 500, "steps": 596336}, {"gen": 135, "nevals": 500, "steps": 857181}, {"gen": 136, "nevals": 500, "steps": 660479}, {"gen": 137, "nevals": 500, "steps": 679994}, {"gen": 138, "nevals": 500, "steps": 587743}, {"gen": 139, "nevals": 500, "steps": 820419}, {"gen": 140, "nevals": 500, "steps": 765386}, {"gen": 141, "nevals": 500, "steps": 823840}, {"gen": 142, "nevals": 500, "steps": 707883}, {"gen": 143, "nevals": 500, "steps": 862124}, {"gen": 144, "nevals": 500, "steps": 715718}, {"gen": 145, "nevals": 500, "steps": 719930}, {"gen": 146, "nevals": 500, "steps": 788051}, {"gen": 147, "nevals": 500, "steps": 773994}, {"gen": 148, "nevals": 500, "steps": 635918}, {"gen": 149, "nevals": 500, "steps": 621937}, {"gen": 150, "nevals": 500, "steps": 695663}, {"gen": 151, "nevals": 500, "steps": 770980}, {"gen": 152, "nevals": 500, "steps": 679266}, {"gen": 153, "nevals": 500, "steps": 662687}, {"gen": 154, "nevals": 500, "steps": 717016}, {"gen": 155, "nevals": 500, "steps": 892412}, {"gen": 156, "nevals": 500, "steps": 895892}, {"gen": 157, "nevals": 500, "steps": 980068}, {"gen": 158, "nevals": 500, "steps": 981495}, {"gen": 159, "nevals": 500, "steps": 823278}, {"gen": 160, "nevals": 500, "steps": 735983}, {"gen": 161, "nevals": 500, "steps": 735138}, {"gen": 162, "nevals": 500, "steps": 787608}, {"gen": 163, "nevals": 500, "steps": 818022}, {"gen": 164, "nevals": 500, "steps": 786363}, {"gen": 165, "nevals": 500, "steps": 892290}, {"gen": 166, "nevals": 500, "steps": 823829}, {"gen": 167, "nevals": 500, "steps": 821678}, {"gen": 168, "nevals": 500, "steps": 795761}, {"gen": 169, "nevals": 500, "steps": 665850}, {"gen": 170, "nevals": 500, "steps": 795078}, {"gen": 171, "nevals": 500, "steps": 742396}, {"gen": 172, "nevals": 500, "steps": 579806}, {"gen": 173, "nevals": 500, "steps": 646363}, {"gen": 174, "nevals": 500, "steps": 660534}, {"gen": 175, "nevals": 500, "steps": 809398}, {"gen": 176, "nevals": 500, "steps": 743352}, {"gen": 177, "nevals": 500, "steps": 793219}, {"gen": 178, "nevals": 500, "steps": 668791}, {"gen": 179, "nevals": 500, "steps": 579397}, {"gen": 180, "nevals": 500, "steps": 739157}, {"gen": 181, "nevals": 500, "steps": 789733}, {"gen": 182, "nevals": 500, "steps": 722604}, {"gen": 183, "nevals": 500, "steps": 799750}, {"gen": 184, "nevals": 500, "steps": 727907}, {"gen": 185, "nevals": 500, "steps": 611083}, {"gen": 186, "nevals": 500, "steps": 694374}, {"gen": 187, "nevals": 500, "steps": 633861}, {"gen": 188, "nevals": 500, "steps": 691740}, {"gen": 189, "nevals": 500, "steps": 799378}, {"gen": 190, "nevals": 500, "steps": 771362}, {"gen": 191, "nevals": 500, "steps": 808470}, {"gen": 192, "nevals": 500, "steps": 887560}, {"gen": 193, "nevals": 500, "steps": 730396}, {"gen": 194, "nevals": 500, "steps": 784825}, {"gen": 195, "nevals": 500, "steps": 645346}, {"gen": 196, "nevals": 500, "steps": 618235}, {"gen": 197, "nevals": 500, "steps": 755751}, {"gen": 198, "nevals": 500, "steps": 653054}, {"gen": 199, "nevals": 500, "steps": 529822}, {"gen": 200, "nevals": 500, "steps": 608044}]